{
	"name": "RAW_Processed",
	"properties": {
		"activities": [
			{
				"name": "Copy data RAW_Processed",
				"type": "Copy",
				"dependsOn": [
					{
						"activity": "Data flow Patients",
						"dependencyConditions": [
							"Succeeded"
						]
					},
					{
						"activity": "Data flow CSVToJSON",
						"dependencyConditions": [
							"Succeeded"
						]
					},
					{
						"activity": "Data flow Caregivers",
						"dependencyConditions": [
							"Succeeded"
						]
					}
				],
				"policy": {
					"timeout": "0.12:00:00",
					"retry": 0,
					"retryIntervalInSeconds": 30,
					"secureOutput": false,
					"secureInput": false
				},
				"userProperties": [],
				"typeProperties": {
					"source": {
						"type": "DelimitedTextSource",
						"storeSettings": {
							"type": "AzureBlobStorageReadSettings",
							"recursive": true,
							"wildcardFolderPath": {
								"value": "@formatDateTime(utcNow(), 'yyyy-MM-dd')",
								"type": "Expression"
							},
							"wildcardFileName": "*.csv",
							"enablePartitionDiscovery": false
						},
						"formatSettings": {
							"type": "DelimitedTextReadSettings"
						}
					},
					"sink": {
						"type": "DelimitedTextSink",
						"storeSettings": {
							"type": "AzureBlobStorageWriteSettings",
							"copyBehavior": "PreserveHierarchy"
						},
						"formatSettings": {
							"type": "DelimitedTextWriteSettings",
							"quoteAllText": true,
							"fileExtension": ".txt"
						}
					},
					"enableStaging": false,
					"translator": {
						"type": "TabularTranslator",
						"typeConversion": true,
						"typeConversionSettings": {
							"allowDataTruncation": true,
							"treatBooleanAsNumber": false
						}
					}
				},
				"inputs": [
					{
						"referenceName": "DS_RAW_F",
						"type": "DatasetReference"
					}
				],
				"outputs": [
					{
						"referenceName": "DS_Processed",
						"type": "DatasetReference"
					}
				]
			},
			{
				"name": "Data flow Patients",
				"type": "ExecuteDataFlow",
				"dependsOn": [],
				"policy": {
					"timeout": "0.12:00:00",
					"retry": 0,
					"retryIntervalInSeconds": 30,
					"secureOutput": false,
					"secureInput": false
				},
				"userProperties": [],
				"typeProperties": {
					"dataflow": {
						"referenceName": "dataflowForPatient",
						"type": "DataFlowReference"
					},
					"compute": {
						"coreCount": 8,
						"computeType": "General"
					},
					"traceLevel": "Fine"
				}
			},
			{
				"name": "Data flow Caregivers",
				"type": "ExecuteDataFlow",
				"dependsOn": [],
				"policy": {
					"timeout": "0.12:00:00",
					"retry": 0,
					"retryIntervalInSeconds": 30,
					"secureOutput": false,
					"secureInput": false
				},
				"userProperties": [],
				"typeProperties": {
					"dataflow": {
						"referenceName": "dataflowForCaregiver",
						"type": "DataFlowReference"
					},
					"compute": {
						"coreCount": 8,
						"computeType": "General"
					},
					"traceLevel": "Fine"
				}
			},
			{
				"name": "Data flow CSVToJSON",
				"type": "ExecuteDataFlow",
				"dependsOn": [],
				"policy": {
					"timeout": "0.12:00:00",
					"retry": 0,
					"retryIntervalInSeconds": 30,
					"secureOutput": false,
					"secureInput": false
				},
				"userProperties": [],
				"typeProperties": {
					"dataflow": {
						"referenceName": "DF_JSONtoCSV",
						"type": "DataFlowReference"
					},
					"compute": {
						"coreCount": 8,
						"computeType": "General"
					},
					"traceLevel": "Fine"
				}
			},
			{
				"name": "UpdateFlagforRAW_Processed",
				"type": "Lookup",
				"dependsOn": [
					{
						"activity": "Copy data RAW_Processed",
						"dependencyConditions": [
							"Succeeded"
						]
					}
				],
				"policy": {
					"timeout": "0.12:00:00",
					"retry": 0,
					"retryIntervalInSeconds": 30,
					"secureOutput": false,
					"secureInput": false
				},
				"userProperties": [],
				"typeProperties": {
					"source": {
						"type": "SnowflakeV2Source",
						"query": "UPDATE DW_GOLD.GOLD_LAYER.PIPELINELOGAUTOMATION \nSET PROCESSED_FLAG = 'Yes' WHERE PIPELINE_ID = 2\nAND PIPELINE_NAME = 'RAW_Processed';",
						"exportSettings": {
							"type": "SnowflakeExportCopyCommand"
						}
					},
					"dataset": {
						"referenceName": "SnowflakeDataset",
						"type": "DatasetReference",
						"parameters": {
							"Tablename": "PIPELINELOGAUTOMATION"
						}
					}
				}
			}
		],
		"annotations": [],
		"lastPublishTime": "2025-05-19T09:19:38Z"
	},
	"type": "Microsoft.DataFactory/factories/pipelines"
}